__init__.py
jsonx/__init__.py
jsonx/modulo.py
json_extracter-1.0.5.dist-info/LICENSE
json_extracter-1.0.5.dist-info/METADATA
json_extracter-1.0.5.dist-info/WHEEL
json_extracter-1.0.5.dist-info/top_level.txt
json_extracter-1.0.5.dist-info/RECORD
