Metadata-Version: 2.1
Name: json_extracter
Version: 1.0.5
Summary: A small example package
Author-email: edyMartin <edgar.edgarroman@gmail.com>
Project-URL: Homepage, https://github.com/pypa/sampleproject
Project-URL: Issues, https://github.com/pypa/sampleproject/issues
Classifier: Programming Language :: Python :: 3
Classifier: License :: OSI Approved :: MIT License
Classifier: Operating System :: OS Independent
Requires-Python: >=3.8
License-File: LICENSE
